Metadata-Version: 1.0
Name: xlsxcompare
Version: 0.0.1
Summary: A Python script to compare the equivalency of two Excel documents
Home-page: UNKNOWN
Author: Bella Woo
Author-email: bella@dharmaplatform.com
License: BSD
Platform: UNKNOWN
